JavabeginnerstutorialZhongwenXilieJiaochengChuyiFix1/README.md
JavabeginnerstutorialZhongwenXilieJiaochengChuyiFix1/__init__.py
JavabeginnerstutorialZhongwenXilieJiaochengChuyiFix1/__main__.py
JavabeginnerstutorialZhongwenXilieJiaochengChuyiFix1/file.epub
JavabeginnerstutorialZhongwenXilieJiaochengChuyiFix1/index.html
JavabeginnerstutorialZhongwenXilieJiaochengChuyiFix1/css/__init__.py
JavabeginnerstutorialZhongwenXilieJiaochengChuyiFix1/css/annotations.css
JavabeginnerstutorialZhongwenXilieJiaochengChuyiFix1/css/main.css
JavabeginnerstutorialZhongwenXilieJiaochengChuyiFix1/css/normalize.css
JavabeginnerstutorialZhongwenXilieJiaochengChuyiFix1/css/popup.css
JavabeginnerstutorialZhongwenXilieJiaochengChuyiFix1/font/__init__.py
JavabeginnerstutorialZhongwenXilieJiaochengChuyiFix1/font/fontello.eot
JavabeginnerstutorialZhongwenXilieJiaochengChuyiFix1/font/fontello.svg
JavabeginnerstutorialZhongwenXilieJiaochengChuyiFix1/font/fontello.ttf
JavabeginnerstutorialZhongwenXilieJiaochengChuyiFix1/font/fontello.woff
JavabeginnerstutorialZhongwenXilieJiaochengChuyiFix1/img/__init__.py
JavabeginnerstutorialZhongwenXilieJiaochengChuyiFix1/img/annotator-glyph-sprite.png
JavabeginnerstutorialZhongwenXilieJiaochengChuyiFix1/img/annotator-icon-sprite.png
JavabeginnerstutorialZhongwenXilieJiaochengChuyiFix1/img/apple-touch-icon.png
JavabeginnerstutorialZhongwenXilieJiaochengChuyiFix1/img/cancelfullscreen.png
JavabeginnerstutorialZhongwenXilieJiaochengChuyiFix1/img/close.png
JavabeginnerstutorialZhongwenXilieJiaochengChuyiFix1/img/fullscreen.png
JavabeginnerstutorialZhongwenXilieJiaochengChuyiFix1/img/loader.gif
JavabeginnerstutorialZhongwenXilieJiaochengChuyiFix1/img/menu-icon.png
JavabeginnerstutorialZhongwenXilieJiaochengChuyiFix1/img/save.png
JavabeginnerstutorialZhongwenXilieJiaochengChuyiFix1/img/saved.png
JavabeginnerstutorialZhongwenXilieJiaochengChuyiFix1/img/settings-s.png
JavabeginnerstutorialZhongwenXilieJiaochengChuyiFix1/img/settings.png
javabeginnerstutorial_zhongwen_xilie_jiaocheng_chuyi_fix1-2025.3.24.1.dist-info/METADATA
javabeginnerstutorial_zhongwen_xilie_jiaocheng_chuyi_fix1-2025.3.24.1.dist-info/WHEEL
javabeginnerstutorial_zhongwen_xilie_jiaocheng_chuyi_fix1-2025.3.24.1.dist-info/entry_points.txt
javabeginnerstutorial_zhongwen_xilie_jiaocheng_chuyi_fix1-2025.3.24.1.dist-info/top_level.txt
javabeginnerstutorial_zhongwen_xilie_jiaocheng_chuyi_fix1-2025.3.24.1.dist-info/RECORD
